mvcgen/__init__.py
mvcgen/agent.py
mvcgen/dotenv.py
mvcgen/models.py
mvcgen/schemas.py
mvcgen/utils.py
mvcgen-0.1.0.dist-info/METADATA
mvcgen-0.1.0.dist-info/WHEEL
mvcgen-0.1.0.dist-info/licenses/LICENSE
mvcgen-0.1.0.dist-info/RECORD
