Metadata-Version: 2.4
Name: mvcgen
Version: 0.1.0
Summary: 一个基于 LangGraph 的智能体框架，支持自然语言数据库操作和 MVC 模式生成
Project-URL: Homepage, https://github.com/your-username/mvcgen
Project-URL: Documentation, https://your-username.github.io/mvcgen
Project-URL: Repository, https://github.com/your-username/mvcgen.git
Project-URL: Issues, https://github.com/your-username/mvcgen/issues
Project-URL: Changelog, https://github.com/your-username/mvcgen/releases
Author-email: mvcgen <mvcgen@example.com>
License-File: LICENSE
Keywords: agent,ai,database,langgraph,mvc,nlp
Classifier: Development Status :: 4 - Beta
Classifier: Intended Audience :: Developers
Classifier: License :: OSI Approved :: MIT License
Classifier: Operating System :: OS Independent
Classifier: Programming Language :: Python :: 3
Classifier: Programming Language :: Python :: 3.9
Classifier: Programming Language :: Python :: 3.10
Classifier: Programming Language :: Python :: 3.11
Classifier: Programming Language :: Python :: 3.12
Classifier: Topic :: Database
Classifier: Topic :: Scientific/Engineering :: Artificial Intelligence
Classifier: Topic :: Software Development :: Libraries :: Python Modules
Requires-Python: >=3.9
Requires-Dist: fastapi>=0.100.0
Requires-Dist: langchain-core>=0.1.0
Requires-Dist: langchain-openai>=0.1.0
Requires-Dist: langgraph>=0.1.0
Requires-Dist: pydantic>=2.0.0
Requires-Dist: python-dotenv>=1.0.0
Requires-Dist: tortoise-orm>=0.20.0
Requires-Dist: uvicorn>=0.20.0
